main.py
keeper_keys-0.2.0.dist-info/METADATA
keeper_keys-0.2.0.dist-info/WHEEL
keeper_keys-0.2.0.dist-info/entry_points.txt
keeper_keys-0.2.0.dist-info/licenses/LICENSE
keeper_keys-0.2.0.dist-info/RECORD
