Metadata-Version: 2.4
Name: keeper-keys
Version: 0.2.0
Summary: KEYS - Straightforward CLI wrapper for Keeper Commander
License-Expression: MIT
License-File: LICENSE
Keywords: cli,environment,keeper,secrets
Classifier: Development Status :: 4 - Beta
Classifier: Environment :: Console
Classifier: Intended Audience :: Developers
Classifier: Programming Language :: Python :: 3
Classifier: Programming Language :: Python :: 3.10
Classifier: Programming Language :: Python :: 3.11
Classifier: Programming Language :: Python :: 3.12
Classifier: Topic :: Security
Classifier: Topic :: Utilities
Requires-Python: >=3.10
